{"pageContext":{"slug":"ru/life/life-blog/","prev":{"id":"50520c91-1d7d-5db3-b152-7506c2fb867e","fileAbsolutePath":"/Users/varya/WebDev/Personal/varya.github.com/content/life/life-in-finland-10/index_en.md","fields":{"slug":"en/life/life-in-finland-10/","prefix":"","lang":"en","disqusIdentifier":"life-life-in-finland-10-index-en","level":1},"frontmatter":{"title":"Finland - driverless busses, free-to-use public laptops, buying drugs in pharmacy","subTitle":null,"v2":true,"old":null}},"next":{"id":"e9abb349-8f5c-5dfb-a9ac-a5e90922f8e0","fileAbsolutePath":"/Users/varya/WebDev/Personal/varya.github.com/content/life/home-finance/index_en.md","fields":{"slug":"en/life/home-finance/","prefix":"","lang":"en","disqusIdentifier":"life-home-finance-index-en","level":1},"frontmatter":{"title":"How we save and spend","subTitle":null,"v2":true,"old":null}}}}